{
    "Han": {
        "pick": 12,
        "pick-perc": "63.2",
        "win": 12,
        "win-perc": "100.0",
        "leader": 3,
        "leader-perc": "25.0",
        "banned": 1,
        "banned-perc": "8.3",
        "first": 0,
        "first-perc": "0.0",
        "last": 0,
        "last-perc": "0.0",
        "1p-win": 0,
        "1p-win-perc": "0.0",
        "5p-win": 0,
        "5p-win-perc": "0.0",
        "user": "<--",
        "monster": "Han",
        "opp_pick": 1,
        "opp_pick-perc": "5.3",
        "opp_win": 0,
        "opp_win-perc": "0.0",
        "opp_leader": 0,
        "opp_leader-perc": "0.0",
        "opp_banned": 0,
        "opp_banned-perc": "0.0",
        "opp_first": 0,
        "opp_first-perc": "0.0",
        "opp_last": 0,
        "opp_last-perc": "0.0",
        "opp_1p-win": 0,
        "opp_1p-win-perc": "0.0",
        "opp_5p-win": 0,
        "opp_5p-win-perc": "0.0"
    },
    "Cheongpung": {
        "pick": 6,
        "pick-perc": "31.6",
        "win": 6,
        "win-perc": "100.0",
        "leader": 0,
        "leader-perc": "0.0",
        "banned": 1,
        "banned-perc": "16.7",
        "first": 0,
        "first-perc": "0.0",
        "last": 0,
        "last-perc": "0.0",
        "1p-win": 0,
        "1p-win-perc": "0.0",
        "5p-win": 0,
        "5p-win-perc": "0.0",
        "user": "<--",
        "monster": "Cheongpung",
        "opp_pick": 7,
        "opp_pick-perc": "36.8",
        "opp_win": 5,
        "opp_win-perc": "71.4",
        "opp_leader": 1,
        "opp_leader-perc": "14.3",
        "opp_banned": 1,
        "opp_banned-perc": "14.3",
        "opp_first": 1,
        "opp_first-perc": "14.3",
        "opp_last": 0,
        "opp_last-perc": "0.0",
        "opp_1p-win": 1,
        "opp_1p-win-perc": "100.0",
        "opp_5p-win": 0,
        "opp_5p-win-perc": "0.0"
    },
    "Zeratu": {
        "pick": 4,
        "pick-perc": "21.1",
        "win": 4,
        "win-perc": "100.0",
        "leader": 0,
        "leader-perc": "0.0",
        "banned": 0,
        "banned-perc": "0.0",
        "first": 0,
        "first-perc": "0.0",
        "last": 0,
        "last-perc": "0.0",
        "1p-win": 0,
        "1p-win-perc": "0.0",
        "5p-win": 0,
        "5p-win-perc": "0.0",
        "user": "<--",
        "monster": "Zeratu",
        "opp_pick": 0,
        "opp_pick-perc": "0.0",
        "opp_win": 0,
        "opp_win-perc": "0.0",
        "opp_leader": 0,
        "opp_leader-perc": "0.0",
        "opp_banned": 0,
        "opp_banned-perc": "0.0",
        "opp_first": 0,
        "opp_first-perc": "0.0",
        "opp_last": 0,
        "opp_last-perc": "0.0",
        "opp_1p-win": 0,
        "opp_1p-win-perc": "0.0",
        "opp_5p-win": 0,
        "opp_5p-win-perc": "0.0"
    },
    "Nephthys": {
        "pick": 7,
        "pick-perc": "36.8",
        "win": 6,
        "win-perc": "85.7",
        "leader": 5,
        "leader-perc": "71.4",
        "banned": 2,
        "banned-perc": "28.6",
        "first": 0,
        "first-perc": "0.0",
        "last": 1,
        "last-perc": "14.3",
        "1p-win": 0,
        "1p-win-perc": "0.0",
        "5p-win": 1,
        "5p-win-perc": "100.0",
        "user": "<--",
        "monster": "Nephthys",
        "opp_pick": 4,
        "opp_pick-perc": "21.1",
        "opp_win": 3,
        "opp_win-perc": "75.0",
        "opp_leader": 3,
        "opp_leader-perc": "75.0",
        "opp_banned": 0,
        "opp_banned-perc": "0.0",
        "opp_first": 1,
        "opp_first-perc": "25.0",
        "opp_last": 0,
        "opp_last-perc": "0.0",
        "opp_1p-win": 0,
        "opp_1p-win-perc": "0.0",
        "opp_5p-win": 0,
        "opp_5p-win-perc": "0.0"
    },
    "Giana": {
        "pick": 18,
        "pick-perc": "94.7",
        "win": 16,
        "win-perc": "88.9",
        "leader": 0,
        "leader-perc": "0.0",
        "banned": 6,
        "banned-perc": "33.3",
        "first": 10,
        "first-perc": "55.6",
        "last": 0,
        "last-perc": "0.0",
        "1p-win": 9,
        "1p-win-perc": "90.0",
        "5p-win": 0,
        "5p-win-perc": "0.0",
        "user": "<--",
        "monster": "Giana",
        "opp_pick": 1,
        "opp_pick-perc": "5.3",
        "opp_win": 1,
        "opp_win-perc": "100.0",
        "opp_leader": 0,
        "opp_leader-perc": "0.0",
        "opp_banned": 0,
        "opp_banned-perc": "0.0",
        "opp_first": 1,
        "opp_first-perc": "100.0",
        "opp_last": 0,
        "opp_last-perc": "0.0",
        "opp_1p-win": 0,
        "opp_1p-win-perc": "0.0",
        "opp_5p-win": 0,
        "opp_5p-win-perc": "0.0"
    },
    "Vanessa": {
        "pick": 0,
        "pick-perc": "0.0",
        "win": 0,
        "win-perc": "0.0",
        "leader": 0,
        "leader-perc": "0.0",
        "banned": 0,
        "banned-perc": "0.0",
        "first": 0,
        "first-perc": "0.0",
        "last": 0,
        "last-perc": "0.0",
        "1p-win": 0,
        "1p-win-perc": "0.0",
        "5p-win": 0,
        "5p-win-perc": "0.0",
        "user": "<--",
        "monster": "Vanessa",
        "opp_pick": 2,
        "opp_pick-perc": "10.5",
        "opp_win": 2,
        "opp_win-perc": "100.0",
        "opp_leader": 2,
        "opp_leader-perc": "100.0",
        "opp_banned": 0,
        "opp_banned-perc": "0.0",
        "opp_first": 1,
        "opp_first-perc": "50.0",
        "opp_last": 1,
        "opp_last-perc": "50.0",
        "opp_1p-win": 0,
        "opp_1p-win-perc": "0.0",
        "opp_5p-win": 0,
        "opp_5p-win-perc": "0.0"
    },
    "Molly": {
        "pick": 6,
        "pick-perc": "31.6",
        "win": 5,
        "win-perc": "83.3",
        "leader": 0,
        "leader-perc": "0.0",
        "banned": 1,
        "banned-perc": "16.7",
        "first": 0,
        "first-perc": "0.0",
        "last": 0,
        "last-perc": "0.0",
        "1p-win": 0,
        "1p-win-perc": "0.0",
        "5p-win": 0,
        "5p-win-perc": "0.0",
        "user": "<--",
        "monster": "Molly",
        "opp_pick": 5,
        "opp_pick-perc": "26.3",
        "opp_win": 4,
        "opp_win-perc": "80.0",
        "opp_leader": 0,
        "opp_leader-perc": "0.0",
        "opp_banned": 1,
        "opp_banned-perc": "20.0",
        "opp_first": 0,
        "opp_first-perc": "0.0",
        "opp_last": 0,
        "opp_last-perc": "0.0",
        "opp_1p-win": 0,
        "opp_1p-win-perc": "0.0",
        "opp_5p-win": 0,
        "opp_5p-win-perc": "0.0"
    },
    "Moore/WaterRYU1": {
        "pick": 0,
        "pick-perc": "0.0",
        "win": 0,
        "win-perc": "0.0",
        "leader": 0,
        "leader-perc": "0.0",
        "banned": 0,
        "banned-perc": "0.0",
        "first": 0,
        "first-perc": "0.0",
        "last": 0,
        "last-perc": "0.0",
        "1p-win": 0,
        "1p-win-perc": "0.0",
        "5p-win": 0,
        "5p-win-perc": "0.0",
        "user": "<--",
        "monster": "Moore/WaterRYU1",
        "opp_pick": 2,
        "opp_pick-perc": "10.5",
        "opp_win": 2,
        "opp_win-perc": "100.0",
        "opp_leader": 0,
        "opp_leader-perc": "0.0",
        "opp_banned": 0,
        "opp_banned-perc": "0.0",
        "opp_first": 0,
        "opp_first-perc": "0.0",
        "opp_last": 0,
        "opp_last-perc": "0.0",
        "opp_1p-win": 0,
        "opp_1p-win-perc": "0.0",
        "opp_5p-win": 0,
        "opp_5p-win-perc": "0.0"
    },
    "Barbara": {
        "pick": 0,
        "pick-perc": "0.0",
        "win": 0,
        "win-perc": "0.0",
        "leader": 0,
        "leader-perc": "0.0",
        "banned": 0,
        "banned-perc": "0.0",
        "first": 0,
        "first-perc": "0.0",
        "last": 0,
        "last-perc": "0.0",
        "1p-win": 0,
        "1p-win-perc": "0.0",
        "5p-win": 0,
        "5p-win-perc": "0.0",
        "user": "<--",
        "monster": "Barbara",
        "opp_pick": 4,
        "opp_pick-perc": "21.1",
        "opp_win": 3,
        "opp_win-perc": "75.0",
        "opp_leader": 0,
        "opp_leader-perc": "0.0",
        "opp_banned": 0,
        "opp_banned-perc": "0.0",
        "opp_first": 0,
        "opp_first-perc": "0.0",
        "opp_last": 0,
        "opp_last-perc": "0.0",
        "opp_1p-win": 0,
        "opp_1p-win-perc": "0.0",
        "opp_5p-win": 0,
        "opp_5p-win-perc": "0.0"
    },
    "Pater": {
        "pick": 6,
        "pick-perc": "31.6",
        "win": 5,
        "win-perc": "83.3",
        "leader": 0,
        "leader-perc": "0.0",
        "banned": 1,
        "banned-perc": "16.7",
        "first": 0,
        "first-perc": "0.0",
        "last": 2,
        "last-perc": "33.3",
        "1p-win": 0,
        "1p-win-perc": "0.0",
        "5p-win": 2,
        "5p-win-perc": "100.0",
        "user": "<--",
        "monster": "Pater",
        "opp_pick": 2,
        "opp_pick-perc": "10.5",
        "opp_win": 2,
        "opp_win-perc": "100.0",
        "opp_leader": 0,
        "opp_leader-perc": "0.0",
        "opp_banned": 1,
        "opp_banned-perc": "50.0",
        "opp_first": 0,
        "opp_first-perc": "0.0",
        "opp_last": 0,
        "opp_last-perc": "0.0",
        "opp_1p-win": 0,
        "opp_1p-win-perc": "0.0",
        "opp_5p-win": 0,
        "opp_5p-win-perc": "0.0"
    },
    "Seara": {
        "pick": 4,
        "pick-perc": "21.1",
        "win": 3,
        "win-perc": "75.0",
        "leader": 1,
        "leader-perc": "25.0",
        "banned": 1,
        "banned-perc": "25.0",
        "first": 0,
        "first-perc": "0.0",
        "last": 1,
        "last-perc": "25.0",
        "1p-win": 0,
        "1p-win-perc": "0.0",
        "5p-win": 1,
        "5p-win-perc": "100.0",
        "user": "<--",
        "monster": "Seara",
        "opp_pick": 4,
        "opp_pick-perc": "21.1",
        "opp_win": 4,
        "opp_win-perc": "100.0",
        "opp_leader": 3,
        "opp_leader-perc": "75.0",
        "opp_banned": 0,
        "opp_banned-perc": "0.0",
        "opp_first": 3,
        "opp_first-perc": "75.0",
        "opp_last": 0,
        "opp_last-perc": "0.0",
        "opp_1p-win": 0,
        "opp_1p-win-perc": "0.0",
        "opp_5p-win": 0,
        "opp_5p-win-perc": "0.0"
    },
    "TianLang": {
        "pick": 4,
        "pick-perc": "21.1",
        "win": 3,
        "win-perc": "75.0",
        "leader": 0,
        "leader-perc": "0.0",
        "banned": 0,
        "banned-perc": "0.0",
        "first": 0,
        "first-perc": "0.0",
        "last": 0,
        "last-perc": "0.0",
        "1p-win": 0,
        "1p-win-perc": "0.0",
        "5p-win": 0,
        "5p-win-perc": "0.0",
        "user": "<--",
        "monster": "TianLang",
        "opp_pick": 1,
        "opp_pick-perc": "5.3",
        "opp_win": 1,
        "opp_win-perc": "100.0",
        "opp_leader": 0,
        "opp_leader-perc": "0.0",
        "opp_banned": 0,
        "opp_banned-perc": "0.0",
        "opp_first": 0,
        "opp_first-perc": "0.0",
        "opp_last": 0,
        "opp_last-perc": "0.0",
        "opp_1p-win": 0,
        "opp_1p-win-perc": "0.0",
        "opp_5p-win": 0,
        "opp_5p-win-perc": "0.0"
    },
    "Akroma": {
        "pick": 4,
        "pick-perc": "21.1",
        "win": 3,
        "win-perc": "75.0",
        "leader": 2,
        "leader-perc": "50.0",
        "banned": 0,
        "banned-perc": "0.0",
        "first": 0,
        "first-perc": "0.0",
        "last": 1,
        "last-perc": "25.0",
        "1p-win": 0,
        "1p-win-perc": "0.0",
        "5p-win": 0,
        "5p-win-perc": "0.0",
        "user": "<--",
        "monster": "Akroma",
        "opp_pick": 0,
        "opp_pick-perc": "0.0",
        "opp_win": 0,
        "opp_win-perc": "0.0",
        "opp_leader": 0,
        "opp_leader-perc": "0.0",
        "opp_banned": 0,
        "opp_banned-perc": "0.0",
        "opp_first": 0,
        "opp_first-perc": "0.0",
        "opp_last": 0,
        "opp_last-perc": "0.0",
        "opp_1p-win": 0,
        "opp_1p-win-perc": "0.0",
        "opp_5p-win": 0,
        "opp_5p-win-perc": "0.0"
    },
    "Tetra": {
        "pick": 1,
        "pick-perc": "5.3",
        "win": 1,
        "win-perc": "100.0",
        "leader": 0,
        "leader-perc": "0.0",
        "banned": 1,
        "banned-perc": "100.0",
        "first": 0,
        "first-perc": "0.0",
        "last": 1,
        "last-perc": "100.0",
        "1p-win": 0,
        "1p-win-perc": "0.0",
        "5p-win": 1,
        "5p-win-perc": "100.0",
        "user": "<--",
        "monster": "Tetra",
        "opp_pick": 3,
        "opp_pick-perc": "15.8",
        "opp_win": 3,
        "opp_win-perc": "100.0",
        "opp_leader": 0,
        "opp_leader-perc": "0.0",
        "opp_banned": 2,
        "opp_banned-perc": "66.7",
        "opp_first": 0,
        "opp_first-perc": "0.0",
        "opp_last": 0,
        "opp_last-perc": "0.0",
        "opp_1p-win": 0,
        "opp_1p-win-perc": "0.0",
        "opp_5p-win": 0,
        "opp_5p-win-perc": "0.0"
    },
    "Ragdoll": {
        "pick": 0,
        "pick-perc": "0.0",
        "win": 0,
        "win-perc": "0.0",
        "leader": 0,
        "leader-perc": "0.0",
        "banned": 0,
        "banned-perc": "0.0",
        "first": 0,
        "first-perc": "0.0",
        "last": 0,
        "last-perc": "0.0",
        "1p-win": 0,
        "1p-win-perc": "0.0",
        "5p-win": 0,
        "5p-win-perc": "0.0",
        "user": "<--",
        "monster": "Ragdoll",
        "opp_pick": 3,
        "opp_pick-perc": "15.8",
        "opp_win": 2,
        "opp_win-perc": "66.7",
        "opp_leader": 0,
        "opp_leader-perc": "0.0",
        "opp_banned": 0,
        "opp_banned-perc": "0.0",
        "opp_first": 0,
        "opp_first-perc": "0.0",
        "opp_last": 0,
        "opp_last-perc": "0.0",
        "opp_1p-win": 0,
        "opp_1p-win-perc": "0.0",
        "opp_5p-win": 0,
        "opp_5p-win-perc": "0.0"
    },
    "Jager": {
        "pick": 0,
        "pick-perc": "0.0",
        "win": 0,
        "win-perc": "0.0",
        "leader": 0,
        "leader-perc": "0.0",
        "banned": 0,
        "banned-perc": "0.0",
        "first": 0,
        "first-perc": "0.0",
        "last": 0,
        "last-perc": "0.0",
        "1p-win": 0,
        "1p-win-perc": "0.0",
        "5p-win": 0,
        "5p-win-perc": "0.0",
        "user": "<--",
        "monster": "Jager",
        "opp_pick": 2,
        "opp_pick-perc": "10.5",
        "opp_win": 2,
        "opp_win-perc": "100.0",
        "opp_leader": 0,
        "opp_leader-perc": "0.0",
        "opp_banned": 1,
        "opp_banned-perc": "50.0",
        "opp_first": 0,
        "opp_first-perc": "0.0",
        "opp_last": 0,
        "opp_last-perc": "0.0",
        "opp_1p-win": 0,
        "opp_1p-win-perc": "0.0",
        "opp_5p-win": 0,
        "opp_5p-win-perc": "0.0"
    },
    "Okeanos": {
        "pick": 1,
        "pick-perc": "5.3",
        "win": 0,
        "win-perc": "0.0",
        "leader": 1,
        "leader-perc": "100.0",
        "banned": 0,
        "banned-perc": "0.0",
        "first": 0,
        "first-perc": "0.0",
        "last": 0,
        "last-perc": "0.0",
        "1p-win": 0,
        "1p-win-perc": "0.0",
        "5p-win": 0,
        "5p-win-perc": "0.0",
        "user": "<--",
        "monster": "Okeanos",
        "opp_pick": 10,
        "opp_pick-perc": "52.6",
        "opp_win": 9,
        "opp_win-perc": "90.0",
        "opp_leader": 3,
        "opp_leader-perc": "30.0",
        "opp_banned": 2,
        "opp_banned-perc": "20.0",
        "opp_first": 1,
        "opp_first-perc": "10.0",
        "opp_last": 0,
        "opp_last-perc": "0.0",
        "opp_1p-win": 0,
        "opp_1p-win-perc": "0.0",
        "opp_5p-win": 0,
        "opp_5p-win-perc": "0.0"
    },
    "Bastet": {
        "pick": 0,
        "pick-perc": "0.0",
        "win": 0,
        "win-perc": "0.0",
        "leader": 0,
        "leader-perc": "0.0",
        "banned": 0,
        "banned-perc": "0.0",
        "first": 0,
        "first-perc": "0.0",
        "last": 0,
        "last-perc": "0.0",
        "1p-win": 0,
        "1p-win-perc": "0.0",
        "5p-win": 0,
        "5p-win-perc": "0.0",
        "user": "<--",
        "monster": "Bastet",
        "opp_pick": 2,
        "opp_pick-perc": "10.5",
        "opp_win": 2,
        "opp_win-perc": "100.0",
        "opp_leader": 0,
        "opp_leader-perc": "0.0",
        "opp_banned": 0,
        "opp_banned-perc": "0.0",
        "opp_first": 1,
        "opp_first-perc": "50.0",
        "opp_last": 0,
        "opp_last-perc": "0.0",
        "opp_1p-win": 0,
        "opp_1p-win-perc": "0.0",
        "opp_5p-win": 0,
        "opp_5p-win-perc": "0.0"
    },
    "Chiwu": {
        "pick": 0,
        "pick-perc": "0.0",
        "win": 0,
        "win-perc": "0.0",
        "leader": 0,
        "leader-perc": "0.0",
        "banned": 0,
        "banned-perc": "0.0",
        "first": 0,
        "first-perc": "0.0",
        "last": 0,
        "last-perc": "0.0",
        "1p-win": 0,
        "1p-win-perc": "0.0",
        "5p-win": 0,
        "5p-win-perc": "0.0",
        "user": "<--",
        "monster": "Chiwu",
        "opp_pick": 3,
        "opp_pick-perc": "15.8",
        "opp_win": 3,
        "opp_win-perc": "100.0",
        "opp_leader": 2,
        "opp_leader-perc": "66.7",
        "opp_banned": 1,
        "opp_banned-perc": "33.3",
        "opp_first": 0,
        "opp_first-perc": "0.0",
        "opp_last": 0,
        "opp_last-perc": "0.0",
        "opp_1p-win": 0,
        "opp_1p-win-perc": "0.0",
        "opp_5p-win": 0,
        "opp_5p-win-perc": "0.0"
    },
    "Poseidon": {
        "pick": 0,
        "pick-perc": "0.0",
        "win": 0,
        "win-perc": "0.0",
        "leader": 0,
        "leader-perc": "0.0",
        "banned": 0,
        "banned-perc": "0.0",
        "first": 0,
        "first-perc": "0.0",
        "last": 0,
        "last-perc": "0.0",
        "1p-win": 0,
        "1p-win-perc": "0.0",
        "5p-win": 0,
        "5p-win-perc": "0.0",
        "user": "<--",
        "monster": "Poseidon",
        "opp_pick": 1,
        "opp_pick-perc": "5.3",
        "opp_win": 1,
        "opp_win-perc": "100.0",
        "opp_leader": 0,
        "opp_leader-perc": "0.0",
        "opp_banned": 0,
        "opp_banned-perc": "0.0",
        "opp_first": 0,
        "opp_first-perc": "0.0",
        "opp_last": 1,
        "opp_last-perc": "100.0",
        "opp_1p-win": 0,
        "opp_1p-win-perc": "0.0",
        "opp_5p-win": 0,
        "opp_5p-win-perc": "0.0"
    },
    "Shimitae": {
        "pick": 0,
        "pick-perc": "0.0",
        "win": 0,
        "win-perc": "0.0",
        "leader": 0,
        "leader-perc": "0.0",
        "banned": 0,
        "banned-perc": "0.0",
        "first": 0,
        "first-perc": "0.0",
        "last": 0,
        "last-perc": "0.0",
        "1p-win": 0,
        "1p-win-perc": "0.0",
        "5p-win": 0,
        "5p-win-perc": "0.0",
        "user": "<--",
        "monster": "Shimitae",
        "opp_pick": 3,
        "opp_pick-perc": "15.8",
        "opp_win": 3,
        "opp_win-perc": "100.0",
        "opp_leader": 1,
        "opp_leader-perc": "33.3",
        "opp_banned": 2,
        "opp_banned-perc": "66.7",
        "opp_first": 0,
        "opp_first-perc": "0.0",
        "opp_last": 0,
        "opp_last-perc": "0.0",
        "opp_1p-win": 0,
        "opp_1p-win-perc": "0.0",
        "opp_5p-win": 0,
        "opp_5p-win-perc": "0.0"
    },
    "Ganymede": {
        "pick": 3,
        "pick-perc": "15.8",
        "win": 2,
        "win-perc": "66.7",
        "leader": 1,
        "leader-perc": "33.3",
        "banned": 0,
        "banned-perc": "0.0",
        "first": 0,
        "first-perc": "0.0",
        "last": 0,
        "last-perc": "0.0",
        "1p-win": 0,
        "1p-win-perc": "0.0",
        "5p-win": 0,
        "5p-win-perc": "0.0",
        "user": "<--",
        "monster": "Ganymede",
        "opp_pick": 0,
        "opp_pick-perc": "0.0",
        "opp_win": 0,
        "opp_win-perc": "0.0",
        "opp_leader": 0,
        "opp_leader-perc": "0.0",
        "opp_banned": 0,
        "opp_banned-perc": "0.0",
        "opp_first": 0,
        "opp_first-perc": "0.0",
        "opp_last": 0,
        "opp_last-perc": "0.0",
        "opp_1p-win": 0,
        "opp_1p-win-perc": "0.0",
        "opp_5p-win": 0,
        "opp_5p-win-perc": "0.0"
    },
    "Lulu": {
        "pick": 0,
        "pick-perc": "0.0",
        "win": 0,
        "win-perc": "0.0",
        "leader": 0,
        "leader-perc": "0.0",
        "banned": 0,
        "banned-perc": "0.0",
        "first": 0,
        "first-perc": "0.0",
        "last": 0,
        "last-perc": "0.0",
        "1p-win": 0,
        "1p-win-perc": "0.0",
        "5p-win": 0,
        "5p-win-perc": "0.0",
        "user": "<--",
        "monster": "Lulu",
        "opp_pick": 1,
        "opp_pick-perc": "5.3",
        "opp_win": 1,
        "opp_win-perc": "100.0",
        "opp_leader": 0,
        "opp_leader-perc": "0.0",
        "opp_banned": 0,
        "opp_banned-perc": "0.0",
        "opp_first": 0,
        "opp_first-perc": "0.0",
        "opp_last": 0,
        "opp_last-perc": "0.0",
        "opp_1p-win": 0,
        "opp_1p-win-perc": "0.0",
        "opp_5p-win": 0,
        "opp_5p-win-perc": "0.0"
    },
    "Miho": {
        "pick": 0,
        "pick-perc": "0.0",
        "win": 0,
        "win-perc": "0.0",
        "leader": 0,
        "leader-perc": "0.0",
        "banned": 0,
        "banned-perc": "0.0",
        "first": 0,
        "first-perc": "0.0",
        "last": 0,
        "last-perc": "0.0",
        "1p-win": 0,
        "1p-win-perc": "0.0",
        "5p-win": 0,
        "5p-win-perc": "0.0",
        "user": "<--",
        "monster": "Miho",
        "opp_pick": 3,
        "opp_pick-perc": "15.8",
        "opp_win": 3,
        "opp_win-perc": "100.0",
        "opp_leader": 0,
        "opp_leader-perc": "0.0",
        "opp_banned": 0,
        "opp_banned-perc": "0.0",
        "opp_first": 0,
        "opp_first-perc": "0.0",
        "opp_last": 2,
        "opp_last-perc": "66.7",
        "opp_1p-win": 0,
        "opp_1p-win-perc": "0.0",
        "opp_5p-win": 0,
        "opp_5p-win-perc": "0.0"
    },
    "Leona": {
        "pick": 2,
        "pick-perc": "10.5",
        "win": 2,
        "win-perc": "100.0",
        "leader": 0,
        "leader-perc": "0.0",
        "banned": 1,
        "banned-perc": "50.0",
        "first": 0,
        "first-perc": "0.0",
        "last": 1,
        "last-perc": "50.0",
        "1p-win": 0,
        "1p-win-perc": "0.0",
        "5p-win": 1,
        "5p-win-perc": "100.0",
        "user": "<--",
        "monster": "Leona",
        "opp_pick": 0,
        "opp_pick-perc": "0.0",
        "opp_win": 0,
        "opp_win-perc": "0.0",
        "opp_leader": 0,
        "opp_leader-perc": "0.0",
        "opp_banned": 0,
        "opp_banned-perc": "0.0",
        "opp_first": 0,
        "opp_first-perc": "0.0",
        "opp_last": 0,
        "opp_last-perc": "0.0",
        "opp_1p-win": 0,
        "opp_1p-win-perc": "0.0",
        "opp_5p-win": 0,
        "opp_5p-win-perc": "0.0"
    },
    "Vigor": {
        "pick": 0,
        "pick-perc": "0.0",
        "win": 0,
        "win-perc": "0.0",
        "leader": 0,
        "leader-perc": "0.0",
        "banned": 0,
        "banned-perc": "0.0",
        "first": 0,
        "first-perc": "0.0",
        "last": 0,
        "last-perc": "0.0",
        "1p-win": 0,
        "1p-win-perc": "0.0",
        "5p-win": 0,
        "5p-win-perc": "0.0",
        "user": "<--",
        "monster": "Vigor",
        "opp_pick": 2,
        "opp_pick-perc": "10.5",
        "opp_win": 2,
        "opp_win-perc": "100.0",
        "opp_leader": 0,
        "opp_leader-perc": "0.0",
        "opp_banned": 0,
        "opp_banned-perc": "0.0",
        "opp_first": 0,
        "opp_first-perc": "0.0",
        "opp_last": 1,
        "opp_last-perc": "50.0",
        "opp_1p-win": 0,
        "opp_1p-win-perc": "0.0",
        "opp_5p-win": 0,
        "opp_5p-win-perc": "0.0"
    },
    "Artamiel": {
        "pick": 5,
        "pick-perc": "26.3",
        "win": 5,
        "win-perc": "100.0",
        "leader": 5,
        "leader-perc": "100.0",
        "banned": 0,
        "banned-perc": "0.0",
        "first": 0,
        "first-perc": "0.0",
        "last": 0,
        "last-perc": "0.0",
        "1p-win": 0,
        "1p-win-perc": "0.0",
        "5p-win": 0,
        "5p-win-perc": "0.0",
        "user": "<--",
        "monster": "Artamiel",
        "opp_pick": 2,
        "opp_pick-perc": "10.5",
        "opp_win": 2,
        "opp_win-perc": "100.0",
        "opp_leader": 0,
        "opp_leader-perc": "0.0",
        "opp_banned": 0,
        "opp_banned-perc": "0.0",
        "opp_first": 0,
        "opp_first-perc": "0.0",
        "opp_last": 0,
        "opp_last-perc": "0.0",
        "opp_1p-win": 0,
        "opp_1p-win-perc": "0.0",
        "opp_5p-win": 0,
        "opp_5p-win-perc": "0.0"
    },
    "Taranys": {
        "pick": 3,
        "pick-perc": "15.8",
        "win": 3,
        "win-perc": "100.0",
        "leader": 0,
        "leader-perc": "0.0",
        "banned": 1,
        "banned-perc": "33.3",
        "first": 0,
        "first-perc": "0.0",
        "last": 0,
        "last-perc": "0.0",
        "1p-win": 0,
        "1p-win-perc": "0.0",
        "5p-win": 0,
        "5p-win-perc": "0.0",
        "user": "<--",
        "monster": "Taranys",
        "opp_pick": 0,
        "opp_pick-perc": "0.0",
        "opp_win": 0,
        "opp_win-perc": "0.0",
        "opp_leader": 0,
        "opp_leader-perc": "0.0",
        "opp_banned": 0,
        "opp_banned-perc": "0.0",
        "opp_first": 0,
        "opp_first-perc": "0.0",
        "opp_last": 0,
        "opp_last-perc": "0.0",
        "opp_1p-win": 0,
        "opp_1p-win-perc": "0.0",
        "opp_5p-win": 0,
        "opp_5p-win-perc": "0.0"
    },
    "Anavel": {
        "pick": 0,
        "pick-perc": "0.0",
        "win": 0,
        "win-perc": "0.0",
        "leader": 0,
        "leader-perc": "0.0",
        "banned": 0,
        "banned-perc": "0.0",
        "first": 0,
        "first-perc": "0.0",
        "last": 0,
        "last-perc": "0.0",
        "1p-win": 0,
        "1p-win-perc": "0.0",
        "5p-win": 0,
        "5p-win-perc": "0.0",
        "user": "<--",
        "monster": "Anavel",
        "opp_pick": 1,
        "opp_pick-perc": "5.3",
        "opp_win": 1,
        "opp_win-perc": "100.0",
        "opp_leader": 0,
        "opp_leader-perc": "0.0",
        "opp_banned": 0,
        "opp_banned-perc": "0.0",
        "opp_first": 0,
        "opp_first-perc": "0.0",
        "opp_last": 0,
        "opp_last-perc": "0.0",
        "opp_1p-win": 0,
        "opp_1p-win-perc": "0.0",
        "opp_5p-win": 0,
        "opp_5p-win-perc": "0.0"
    },
    "Leo": {
        "pick": 4,
        "pick-perc": "21.1",
        "win": 4,
        "win-perc": "100.0",
        "leader": 0,
        "leader-perc": "0.0",
        "banned": 3,
        "banned-perc": "75.0",
        "first": 0,
        "first-perc": "0.0",
        "last": 1,
        "last-perc": "25.0",
        "1p-win": 0,
        "1p-win-perc": "0.0",
        "5p-win": 1,
        "5p-win-perc": "100.0",
        "user": "<--",
        "monster": "Leo",
        "opp_pick": 1,
        "opp_pick-perc": "5.3",
        "opp_win": 1,
        "opp_win-perc": "100.0",
        "opp_leader": 1,
        "opp_leader-perc": "100.0",
        "opp_banned": 0,
        "opp_banned-perc": "0.0",
        "opp_first": 0,
        "opp_first-perc": "0.0",
        "opp_last": 0,
        "opp_last-perc": "0.0",
        "opp_1p-win": 0,
        "opp_1p-win-perc": "0.0",
        "opp_5p-win": 0,
        "opp_5p-win-perc": "0.0"
    },
    "Laika": {
        "pick": 0,
        "pick-perc": "0.0",
        "win": 0,
        "win-perc": "0.0",
        "leader": 0,
        "leader-perc": "0.0",
        "banned": 0,
        "banned-perc": "0.0",
        "first": 0,
        "first-perc": "0.0",
        "last": 0,
        "last-perc": "0.0",
        "1p-win": 0,
        "1p-win-perc": "0.0",
        "5p-win": 0,
        "5p-win-perc": "0.0",
        "user": "<--",
        "monster": "Laika",
        "opp_pick": 1,
        "opp_pick-perc": "5.3",
        "opp_win": 1,
        "opp_win-perc": "100.0",
        "opp_leader": 0,
        "opp_leader-perc": "0.0",
        "opp_banned": 0,
        "opp_banned-perc": "0.0",
        "opp_first": 0,
        "opp_first-perc": "0.0",
        "opp_last": 1,
        "opp_last-perc": "100.0",
        "opp_1p-win": 0,
        "opp_1p-win-perc": "0.0",
        "opp_5p-win": 0,
        "opp_5p-win-perc": "0.0"
    },
    "Fran": {
        "pick": 0,
        "pick-perc": "0.0",
        "win": 0,
        "win-perc": "0.0",
        "leader": 0,
        "leader-perc": "0.0",
        "banned": 0,
        "banned-perc": "0.0",
        "first": 0,
        "first-perc": "0.0",
        "last": 0,
        "last-perc": "0.0",
        "1p-win": 0,
        "1p-win-perc": "0.0",
        "5p-win": 0,
        "5p-win-perc": "0.0",
        "user": "<--",
        "monster": "Fran",
        "opp_pick": 3,
        "opp_pick-perc": "15.8",
        "opp_win": 3,
        "opp_win-perc": "100.0",
        "opp_leader": 0,
        "opp_leader-perc": "0.0",
        "opp_banned": 2,
        "opp_banned-perc": "66.7",
        "opp_first": 0,
        "opp_first-perc": "0.0",
        "opp_last": 0,
        "opp_last-perc": "0.0",
        "opp_1p-win": 0,
        "opp_1p-win-perc": "0.0",
        "opp_5p-win": 0,
        "opp_5p-win-perc": "0.0"
    },
    "Velajuel": {
        "pick": 0,
        "pick-perc": "0.0",
        "win": 0,
        "win-perc": "0.0",
        "leader": 0,
        "leader-perc": "0.0",
        "banned": 0,
        "banned-perc": "0.0",
        "first": 0,
        "first-perc": "0.0",
        "last": 0,
        "last-perc": "0.0",
        "1p-win": 0,
        "1p-win-perc": "0.0",
        "5p-win": 0,
        "5p-win-perc": "0.0",
        "user": "<--",
        "monster": "Velajuel",
        "opp_pick": 2,
        "opp_pick-perc": "10.5",
        "opp_win": 1,
        "opp_win-perc": "50.0",
        "opp_leader": 1,
        "opp_leader-perc": "50.0",
        "opp_banned": 1,
        "opp_banned-perc": "50.0",
        "opp_first": 0,
        "opp_first-perc": "0.0",
        "opp_last": 1,
        "opp_last-perc": "50.0",
        "opp_1p-win": 0,
        "opp_1p-win-perc": "0.0",
        "opp_5p-win": 1,
        "opp_5p-win-perc": "100.0"
    },
    "QitianDasheng": {
        "pick": 0,
        "pick-perc": "0.0",
        "win": 0,
        "win-perc": "0.0",
        "leader": 0,
        "leader-perc": "0.0",
        "banned": 0,
        "banned-perc": "0.0",
        "first": 0,
        "first-perc": "0.0",
        "last": 0,
        "last-perc": "0.0",
        "1p-win": 0,
        "1p-win-perc": "0.0",
        "5p-win": 0,
        "5p-win-perc": "0.0",
        "user": "<--",
        "monster": "QitianDasheng",
        "opp_pick": 1,
        "opp_pick-perc": "5.3",
        "opp_win": 1,
        "opp_win-perc": "100.0",
        "opp_leader": 1,
        "opp_leader-perc": "100.0",
        "opp_banned": 0,
        "opp_banned-perc": "0.0",
        "opp_first": 0,
        "opp_first-perc": "0.0",
        "opp_last": 0,
        "opp_last-perc": "0.0",
        "opp_1p-win": 0,
        "opp_1p-win-perc": "0.0",
        "opp_5p-win": 0,
        "opp_5p-win-perc": "0.0"
    },
    "Bering": {
        "pick": 0,
        "pick-perc": "0.0",
        "win": 0,
        "win-perc": "0.0",
        "leader": 0,
        "leader-perc": "0.0",
        "banned": 0,
        "banned-perc": "0.0",
        "first": 0,
        "first-perc": "0.0",
        "last": 0,
        "last-perc": "0.0",
        "1p-win": 0,
        "1p-win-perc": "0.0",
        "5p-win": 0,
        "5p-win-perc": "0.0",
        "user": "<--",
        "monster": "Bering",
        "opp_pick": 1,
        "opp_pick-perc": "5.3",
        "opp_win": 0,
        "opp_win-perc": "0.0",
        "opp_leader": 0,
        "opp_leader-perc": "0.0",
        "opp_banned": 1,
        "opp_banned-perc": "100.0",
        "opp_first": 0,
        "opp_first-perc": "0.0",
        "opp_last": 0,
        "opp_last-perc": "0.0",
        "opp_1p-win": 0,
        "opp_1p-win-perc": "0.0",
        "opp_5p-win": 0,
        "opp_5p-win-perc": "0.0"
    },
    "Woonsa": {
        "pick": 1,
        "pick-perc": "5.3",
        "win": 1,
        "win-perc": "100.0",
        "leader": 0,
        "leader-perc": "0.0",
        "banned": 0,
        "banned-perc": "0.0",
        "first": 0,
        "first-perc": "0.0",
        "last": 0,
        "last-perc": "0.0",
        "1p-win": 0,
        "1p-win-perc": "0.0",
        "5p-win": 0,
        "5p-win-perc": "0.0",
        "user": "<--",
        "monster": "Woonsa",
        "opp_pick": 1,
        "opp_pick-perc": "5.3",
        "opp_win": 1,
        "opp_win-perc": "100.0",
        "opp_leader": 0,
        "opp_leader-perc": "0.0",
        "opp_banned": 1,
        "opp_banned-perc": "100.0",
        "opp_first": 0,
        "opp_first-perc": "0.0",
        "opp_last": 0,
        "opp_last-perc": "0.0",
        "opp_1p-win": 0,
        "opp_1p-win-perc": "0.0",
        "opp_5p-win": 0,
        "opp_5p-win-perc": "0.0"
    },
    "Verdehile": {
        "pick": 1,
        "pick-perc": "5.3",
        "win": 1,
        "win-perc": "100.0",
        "leader": 0,
        "leader-perc": "0.0",
        "banned": 0,
        "banned-perc": "0.0",
        "first": 0,
        "first-perc": "0.0",
        "last": 0,
        "last-perc": "0.0",
        "1p-win": 0,
        "1p-win-perc": "0.0",
        "5p-win": 0,
        "5p-win-perc": "0.0",
        "user": "<--",
        "monster": "Verdehile",
        "opp_pick": 2,
        "opp_pick-perc": "10.5",
        "opp_win": 2,
        "opp_win-perc": "100.0",
        "opp_leader": 0,
        "opp_leader-perc": "0.0",
        "opp_banned": 1,
        "opp_banned-perc": "50.0",
        "opp_first": 0,
        "opp_first-perc": "0.0",
        "opp_last": 1,
        "opp_last-perc": "50.0",
        "opp_1p-win": 0,
        "opp_1p-win-perc": "0.0",
        "opp_5p-win": 0,
        "opp_5p-win-perc": "0.0"
    },
    "Triana": {
        "pick": 2,
        "pick-perc": "10.5",
        "win": 2,
        "win-perc": "100.0",
        "leader": 0,
        "leader-perc": "0.0",
        "banned": 0,
        "banned-perc": "0.0",
        "first": 0,
        "first-perc": "0.0",
        "last": 0,
        "last-perc": "0.0",
        "1p-win": 0,
        "1p-win-perc": "0.0",
        "5p-win": 0,
        "5p-win-perc": "0.0",
        "user": "<--",
        "monster": "Triana",
        "opp_pick": 1,
        "opp_pick-perc": "5.3",
        "opp_win": 1,
        "opp_win-perc": "100.0",
        "opp_leader": 0,
        "opp_leader-perc": "0.0",
        "opp_banned": 0,
        "opp_banned-perc": "0.0",
        "opp_first": 0,
        "opp_first-perc": "0.0",
        "opp_last": 1,
        "opp_last-perc": "100.0",
        "opp_1p-win": 0,
        "opp_1p-win-perc": "0.0",
        "opp_5p-win": 0,
        "opp_5p-win-perc": "0.0"
    },
    "Kahli": {
        "pick": 0,
        "pick-perc": "0.0",
        "win": 0,
        "win-perc": "0.0",
        "leader": 0,
        "leader-perc": "0.0",
        "banned": 0,
        "banned-perc": "0.0",
        "first": 0,
        "first-perc": "0.0",
        "last": 0,
        "last-perc": "0.0",
        "1p-win": 0,
        "1p-win-perc": "0.0",
        "5p-win": 0,
        "5p-win-perc": "0.0",
        "user": "<--",
        "monster": "Kahli",
        "opp_pick": 2,
        "opp_pick-perc": "10.5",
        "opp_win": 2,
        "opp_win-perc": "100.0",
        "opp_leader": 0,
        "opp_leader-perc": "0.0",
        "opp_banned": 1,
        "opp_banned-perc": "50.0",
        "opp_first": 0,
        "opp_first-perc": "0.0",
        "opp_last": 0,
        "opp_last-perc": "0.0",
        "opp_1p-win": 0,
        "opp_1p-win-perc": "0.0",
        "opp_5p-win": 0,
        "opp_5p-win-perc": "0.0"
    },
    "Gemini": {
        "pick": 0,
        "pick-perc": "0.0",
        "win": 0,
        "win-perc": "0.0",
        "leader": 0,
        "leader-perc": "0.0",
        "banned": 0,
        "banned-perc": "0.0",
        "first": 0,
        "first-perc": "0.0",
        "last": 0,
        "last-perc": "0.0",
        "1p-win": 0,
        "1p-win-perc": "0.0",
        "5p-win": 0,
        "5p-win-perc": "0.0",
        "user": "<--",
        "monster": "Gemini",
        "opp_pick": 2,
        "opp_pick-perc": "10.5",
        "opp_win": 2,
        "opp_win-perc": "100.0",
        "opp_leader": 0,
        "opp_leader-perc": "0.0",
        "opp_banned": 0,
        "opp_banned-perc": "0.0",
        "opp_first": 0,
        "opp_first-perc": "0.0",
        "opp_last": 0,
        "opp_last-perc": "0.0",
        "opp_1p-win": 0,
        "opp_1p-win-perc": "0.0",
        "opp_5p-win": 0,
        "opp_5p-win-perc": "0.0"
    },
    "Leah/LightCHUN-LI1": {
        "pick": 0,
        "pick-perc": "0.0",
        "win": 0,
        "win-perc": "0.0",
        "leader": 0,
        "leader-perc": "0.0",
        "banned": 0,
        "banned-perc": "0.0",
        "first": 0,
        "first-perc": "0.0",
        "last": 0,
        "last-perc": "0.0",
        "1p-win": 0,
        "1p-win-perc": "0.0",
        "5p-win": 0,
        "5p-win-perc": "0.0",
        "user": "<--",
        "monster": "Leah/LightCHUN-LI1",
        "opp_pick": 2,
        "opp_pick-perc": "10.5",
        "opp_win": 2,
        "opp_win-perc": "100.0",
        "opp_leader": 0,
        "opp_leader-perc": "0.0",
        "opp_banned": 0,
        "opp_banned-perc": "0.0",
        "opp_first": 0,
        "opp_first-perc": "0.0",
        "opp_last": 0,
        "opp_last-perc": "0.0",
        "opp_1p-win": 0,
        "opp_1p-win-perc": "0.0",
        "opp_5p-win": 0,
        "opp_5p-win-perc": "0.0"
    },
    "Hathor": {
        "pick": 0,
        "pick-perc": "0.0",
        "win": 0,
        "win-perc": "0.0",
        "leader": 0,
        "leader-perc": "0.0",
        "banned": 0,
        "banned-perc": "0.0",
        "first": 0,
        "first-perc": "0.0",
        "last": 0,
        "last-perc": "0.0",
        "1p-win": 0,
        "1p-win-perc": "0.0",
        "5p-win": 0,
        "5p-win-perc": "0.0",
        "user": "<--",
        "monster": "Hathor",
        "opp_pick": 2,
        "opp_pick-perc": "10.5",
        "opp_win": 2,
        "opp_win-perc": "100.0",
        "opp_leader": 0,
        "opp_leader-perc": "0.0",
        "opp_banned": 1,
        "opp_banned-perc": "50.0",
        "opp_first": 0,
        "opp_first-perc": "0.0",
        "opp_last": 0,
        "opp_last-perc": "0.0",
        "opp_1p-win": 0,
        "opp_1p-win-perc": "0.0",
        "opp_5p-win": 0,
        "opp_5p-win-perc": "0.0"
    },
    "Sian": {
        "pick": 0,
        "pick-perc": "0.0",
        "win": 0,
        "win-perc": "0.0",
        "leader": 0,
        "leader-perc": "0.0",
        "banned": 0,
        "banned-perc": "0.0",
        "first": 0,
        "first-perc": "0.0",
        "last": 0,
        "last-perc": "0.0",
        "1p-win": 0,
        "1p-win-perc": "0.0",
        "5p-win": 0,
        "5p-win-perc": "0.0",
        "user": "<--",
        "monster": "Sian",
        "opp_pick": 1,
        "opp_pick-perc": "5.3",
        "opp_win": 1,
        "opp_win-perc": "100.0",
        "opp_leader": 0,
        "opp_leader-perc": "0.0",
        "opp_banned": 0,
        "opp_banned-perc": "0.0",
        "opp_first": 0,
        "opp_first-perc": "0.0",
        "opp_last": 0,
        "opp_last-perc": "0.0",
        "opp_1p-win": 0,
        "opp_1p-win-perc": "0.0",
        "opp_5p-win": 0,
        "opp_5p-win-perc": "0.0"
    },
    "Juno": {
        "pick": 1,
        "pick-perc": "5.3",
        "win": 1,
        "win-perc": "100.0",
        "leader": 1,
        "leader-perc": "100.0",
        "banned": 0,
        "banned-perc": "0.0",
        "first": 0,
        "first-perc": "0.0",
        "last": 1,
        "last-perc": "100.0",
        "1p-win": 0,
        "1p-win-perc": "0.0",
        "5p-win": 1,
        "5p-win-perc": "100.0",
        "user": "<--",
        "monster": "Juno",
        "opp_pick": 1,
        "opp_pick-perc": "5.3",
        "opp_win": 1,
        "opp_win-perc": "100.0",
        "opp_leader": 0,
        "opp_leader-perc": "0.0",
        "opp_banned": 0,
        "opp_banned-perc": "0.0",
        "opp_first": 0,
        "opp_first-perc": "0.0",
        "opp_last": 0,
        "opp_last-perc": "0.0",
        "opp_1p-win": 0,
        "opp_1p-win-perc": "0.0",
        "opp_5p-win": 0,
        "opp_5p-win-perc": "0.0"
    },
    "Bellenus": {
        "pick": 0,
        "pick-perc": "0.0",
        "win": 0,
        "win-perc": "0.0",
        "leader": 0,
        "leader-perc": "0.0",
        "banned": 0,
        "banned-perc": "0.0",
        "first": 0,
        "first-perc": "0.0",
        "last": 0,
        "last-perc": "0.0",
        "1p-win": 0,
        "1p-win-perc": "0.0",
        "5p-win": 0,
        "5p-win-perc": "0.0",
        "user": "<--",
        "monster": "Bellenus",
        "opp_pick": 1,
        "opp_pick-perc": "5.3",
        "opp_win": 1,
        "opp_win-perc": "100.0",
        "opp_leader": 0,
        "opp_leader-perc": "0.0",
        "opp_banned": 0,
        "opp_banned-perc": "0.0",
        "opp_first": 0,
        "opp_first-perc": "0.0",
        "opp_last": 0,
        "opp_last-perc": "0.0",
        "opp_1p-win": 0,
        "opp_1p-win-perc": "0.0",
        "opp_5p-win": 0,
        "opp_5p-win-perc": "0.0"
    },
    "Rica": {
        "pick": 0,
        "pick-perc": "0.0",
        "win": 0,
        "win-perc": "0.0",
        "leader": 0,
        "leader-perc": "0.0",
        "banned": 0,
        "banned-perc": "0.0",
        "first": 0,
        "first-perc": "0.0",
        "last": 0,
        "last-perc": "0.0",
        "1p-win": 0,
        "1p-win-perc": "0.0",
        "5p-win": 0,
        "5p-win-perc": "0.0",
        "user": "<--",
        "monster": "Rica",
        "opp_pick": 1,
        "opp_pick-perc": "5.3",
        "opp_win": 1,
        "opp_win-perc": "100.0",
        "opp_leader": 0,
        "opp_leader-perc": "0.0",
        "opp_banned": 0,
        "opp_banned-perc": "0.0",
        "opp_first": 0,
        "opp_first-perc": "0.0",
        "opp_last": 0,
        "opp_last-perc": "0.0",
        "opp_1p-win": 0,
        "opp_1p-win-perc": "0.0",
        "opp_5p-win": 0,
        "opp_5p-win-perc": "0.0"
    },
    "XingZhe": {
        "pick": 0,
        "pick-perc": "0.0",
        "win": 0,
        "win-perc": "0.0",
        "leader": 0,
        "leader-perc": "0.0",
        "banned": 0,
        "banned-perc": "0.0",
        "first": 0,
        "first-perc": "0.0",
        "last": 0,
        "last-perc": "0.0",
        "1p-win": 0,
        "1p-win-perc": "0.0",
        "5p-win": 0,
        "5p-win-perc": "0.0",
        "user": "<--",
        "monster": "XingZhe",
        "opp_pick": 1,
        "opp_pick-perc": "5.3",
        "opp_win": 1,
        "opp_win-perc": "100.0",
        "opp_leader": 1,
        "opp_leader-perc": "100.0",
        "opp_banned": 0,
        "opp_banned-perc": "0.0",
        "opp_first": 0,
        "opp_first-perc": "0.0",
        "opp_last": 1,
        "opp_last-perc": "100.0",
        "opp_1p-win": 0,
        "opp_1p-win-perc": "0.0",
        "opp_5p-win": 0,
        "opp_5p-win-perc": "0.0"
    }
}